LICENSE.txt
README.md
setup.py
bin/eg
eg/__init__.py
eg/__main__.py
eg/color.py
eg/config.py
eg/core.py
eg/eg_exec.py
eg/substitute.py
eg/util.py
eg.egg-info/PKG-INFO
eg.egg-info/SOURCES.txt
eg.egg-info/dependency_links.txt
eg.egg-info/not-zip-safe
eg.egg-info/top_level.txt
eg/examples/adb.md
eg/examples/aliases.json
eg/examples/awk.md
eg/examples/brctl.md
eg/examples/brew.md
eg/examples/cat.md
eg/examples/cd.md
eg/examples/chmod.md
eg/examples/chown.md
eg/examples/clip-view.md
eg/examples/cp.md
eg/examples/curl.md
eg/examples/cut.md
eg/examples/date.md
eg/examples/dd.md
eg/examples/df.md
eg/examples/diff.md
eg/examples/dig.md
eg/examples/du.md
eg/examples/echo.md
eg/examples/eg.md
eg/examples/expand.md
eg/examples/file.md
eg/examples/find.md
eg/examples/free.md
eg/examples/gcc.md
eg/examples/git.md
eg/examples/grep.md
eg/examples/gzip.md
eg/examples/head.md
eg/examples/hexdump.md
eg/examples/ifconfig.md
eg/examples/ip.md
eg/examples/keytool.md
eg/examples/kill.md
eg/examples/less.md
eg/examples/ln.md
eg/examples/locate.md
eg/examples/ls.md
eg/examples/mkdir.md
eg/examples/more.md
eg/examples/mv.md
eg/examples/nc.md
eg/examples/nice.md
eg/examples/od.md
eg/examples/patch.md
eg/examples/ping.md
eg/examples/prqlc.md
eg/examples/ps.md
eg/examples/pwd.md
eg/examples/renice.md
eg/examples/rm.md
eg/examples/rsync.md
eg/examples/scp.md
eg/examples/set.md
eg/examples/sort.md
eg/examples/strace.md
eg/examples/su.md
eg/examples/sudo.md
eg/examples/tail.md
eg/examples/tar.md
eg/examples/time.md
eg/examples/top.md
eg/examples/touch.md
eg/examples/tr.md
eg/examples/uniq.md
eg/examples/unzip.md
eg/examples/virtualenv.md
eg/examples/wc.md
eg/examples/wget.md
eg/examples/whatis.md
eg/examples/whereis.md
eg/examples/which.md
eg/examples/xargs.md
eg/examples/zip.md