Metadata-Version: 2.2
Name: eg
Version: 1.2.3
Summary: Examples at the command line
Home-page: https://github.com/srsudar/eg
Author: Sam Sudar
Author-email: sudar.sam@gmail.com
License: MIT
License-File: LICENSE.txt
Dynamic: author
Dynamic: author-email
Dynamic: description
Dynamic: home-page
Dynamic: license
Dynamic: summary
